dookumentation.py
setup.py
dookumentation.egg-info/PKG-INFO
dookumentation.egg-info/SOURCES.txt
dookumentation.egg-info/dependency_links.txt
dookumentation.egg-info/requires.txt
dookumentation.egg-info/top_level.txt
dookumentation.egg-info/zip-safe